{"provider_id":35514,"name":"Prince C Rohan","provider_specialty":"Hematology","visit_count":23}
{"provider_id":67167,"name":"Retta C Borer","provider_specialty":"Hematology","visit_count":18}
{"provider_id":70395,"name":"Jorge B Stark","provider_specialty":"Hematology","visit_count":16}
{"provider_id":19922,"name":"Osvaldo B Ward","provider_specialty":"Hematology","visit_count":30}
{"provider_id":10994,"name":"Jett C Wolf","provider_specialty":"Hematology","visit_count":16}
{"provider_id":13104,"name":"Tia B Schmitt","provider_specialty":"Hematology","visit_count":16}
{"provider_id":5880,"name":"Susie B Gibson","provider_specialty":"Hematology","visit_count":18}
{"provider_id":25322,"name":"Phoebe A Huel","provider_specialty":"Hematology","visit_count":20}
{"provider_id":98005,"name":"Ruthe C Kihn","provider_specialty":"Hematology","visit_count":19}
{"provider_id":73212,"name":"Karolann A Oberbrunner","provider_specialty":"Hematology","visit_count":27}
{"provider_id":26910,"name":"Cielo B Connelly","provider_specialty":"Hematology","visit_count":23}
{"provider_id":53538,"name":"Millie C Gibson","provider_specialty":"Hematology","visit_count":23}
{"provider_id":73508,"name":"Houston B Wilkinson","provider_specialty":"Hematology","visit_count":19}
{"provider_id":21326,"name":"Granville B Keeling","provider_specialty":"Hematology","visit_count":30}
{"provider_id":72755,"name":"Adelbert A Watsica","provider_specialty":"Hematology","visit_count":26}
{"provider_id":37787,"name":"Darrin A Cummerata","provider_specialty":"Hematology","visit_count":25}
{"provider_id":81617,"name":"Ernie C Bechtelar","provider_specialty":"Hematology","visit_count":22}
{"provider_id":65395,"name":"Dayana C Prohaska","provider_specialty":"Hematology","visit_count":21}
{"provider_id":6506,"name":"Frank A Kshlerin","provider_specialty":"Hematology","visit_count":20}
{"provider_id":33475,"name":"Cristobal A Reichel","provider_specialty":"Hematology","visit_count":24}
{"provider_id":402,"name":"Shanel A Hodkiewicz","provider_specialty":"Hematology","visit_count":19}
{"provider_id":4692,"name":"Harrison A Von","provider_specialty":"Hematology","visit_count":30}
{"provider_id":76886,"name":"Herta C Russel","provider_specialty":"Hematology","visit_count":15}
{"provider_id":48916,"name":"Delfina B O'Reilly","provider_specialty":"Hematology","visit_count":21}
{"provider_id":19534,"name":"Elsie A Collins","provider_specialty":"Hematology","visit_count":16}
{"provider_id":83857,"name":"Maida C Krajcik","provider_specialty":"Hematology","visit_count":27}
{"provider_id":10475,"name":"Marilou B Cole","provider_specialty":"Hematology","visit_count":24}
{"provider_id":8296,"name":"Jerod A Miller","provider_specialty":"Hematology","visit_count":17}
{"provider_id":21544,"name":"Ken B Heidenreich","provider_specialty":"Hematology","visit_count":16}
{"provider_id":12110,"name":"Edna A Jacobi","provider_specialty":"Hematology","visit_count":25}
{"provider_id":36043,"name":"Asha A Powlowski","provider_specialty":"Hematology","visit_count":29}
{"provider_id":5923,"name":"Lulu C Oberbrunner","provider_specialty":"Hematology","visit_count":22}
{"provider_id":67012,"name":"Javon C Wisozk","provider_specialty":"Hematology","visit_count":25}
{"provider_id":48282,"name":"Jensen A Kunze","provider_specialty":"Hematology","visit_count":21}
{"provider_id":34853,"name":"Julianne C Bins","provider_specialty":"Hematology","visit_count":15}
{"provider_id":97086,"name":"Clinton A Borer","provider_specialty":"Hematology","visit_count":28}
{"provider_id":16935,"name":"Trisha A Zulauf","provider_specialty":"Hematology","visit_count":28}
{"provider_id":13871,"name":"Patricia C Kerluke","provider_specialty":"Hematology","visit_count":24}
{"provider_id":76524,"name":"Tyrell C Kutch","provider_specialty":"Hematology","visit_count":28}
{"provider_id":44769,"name":"Eliseo A Ruecker","provider_specialty":"Hematology","visit_count":15}
{"provider_id":82503,"name":"Kory C Willms","provider_specialty":"Hematology","visit_count":18}
{"provider_id":92849,"name":"Tyrique C Nikolaus","provider_specialty":"Hematology","visit_count":18}
{"provider_id":38457,"name":"Brooke C Krajcik","provider_specialty":"Hematology","visit_count":17}
{"provider_id":56510,"name":"Millie C Breitenberg","provider_specialty":"Hematology","visit_count":22}
{"provider_id":81698,"name":"Jude A Koepp","provider_specialty":"Hematology","visit_count":20}
{"provider_id":95604,"name":"Heidi A Ledner","provider_specialty":"Hematology","visit_count":15}
{"provider_id":89977,"name":"Jefferey A Bechtelar","provider_specialty":"Hematology","visit_count":19}
{"provider_id":90683,"name":"Lennie C Kunde","provider_specialty":"Hematology","visit_count":15}
{"provider_id":24003,"name":"Selina B Johns","provider_specialty":"Hematology","visit_count":25}
{"provider_id":36479,"name":"Haven A Fisher","provider_specialty":"Hematology","visit_count":26}
{"provider_id":49300,"name":"Jamaal C Bayer","provider_specialty":"Hematology","visit_count":28}
{"provider_id":54761,"name":"Verlie C Carter","provider_specialty":"Hematology","visit_count":29}
{"provider_id":42612,"name":"Wilson A Schaden","provider_specialty":"Hematology","visit_count":26}
{"provider_id":80304,"name":"Hosea B Funk","provider_specialty":"Hematology","visit_count":28}
{"provider_id":57438,"name":"Carter A Schowalter","provider_specialty":"Hematology","visit_count":30}
{"provider_id":75574,"name":"Helmer A McGlynn","provider_specialty":"Hematology","visit_count":17}
{"provider_id":2263,"name":"Joe B Hirthe","provider_specialty":"Hematology","visit_count":16}
{"provider_id":4434,"name":"Jamel A Will","provider_specialty":"Hematology","visit_count":17}
{"provider_id":59669,"name":"Adrian A Purdy","provider_specialty":"Hematology","visit_count":29}
{"provider_id":38527,"name":"Joy B Cole","provider_specialty":"Hematology","visit_count":24}
{"provider_id":16111,"name":"Madyson A Pollich","provider_specialty":"Hematology","visit_count":26}
{"provider_id":18934,"name":"Valerie C Yost","provider_specialty":"Hematology","visit_count":20}
{"provider_id":86440,"name":"Dalton B Moore","provider_specialty":"Hematology","visit_count":45}
{"provider_id":81649,"name":"Cecilia B Willms","provider_specialty":"Hematology","visit_count":19}
{"provider_id":56752,"name":"Alanna A Nolan","provider_specialty":"Hematology","visit_count":15}
{"provider_id":7166,"name":"Burnice B Marvin","provider_specialty":"Hematology","visit_count":24}
